Metadata-Version: 2.1
Name: jatsutils
Version: 0.0.1
Summary: Utility for obtain JATS XML data
Home-page: https://github.com/cccaballero/jatsutils
Author: Carlos Cesar Caballero
Author-email: ccesar@daxslab.com
License: UNKNOWN
Platform: UNKNOWN
Classifier: Programming Language :: Python :: 3
Classifier: License :: OSI Approved :: MIT License
Classifier: Operating System :: OS Independent
Provides-Extra: dev
